pydiblis/__init__.py
pydiblis/pydiblis.py
pydiblis-0.7.dist-info/METADATA
pydiblis-0.7.dist-info/WHEEL
pydiblis-0.7.dist-info/top_level.txt
pydiblis-0.7.dist-info/RECORD
