Metadata-Version: 2.1
Name: pydiblis
Version: 0.7
Summary: Tool box for python
Author: Sh
Author-email: shcyberconquerors@gmail.com
Keywords: python
Classifier: Development Status :: 1 - Planning
Classifier: Intended Audience :: Developers
Classifier: Programming Language :: Python :: 3
Classifier: Operating System :: Unix
Classifier: Operating System :: MacOS :: MacOS X
Classifier: Operating System :: Microsoft :: Windows
Requires-Dist: requests
Requires-Dist: Crypto.Cipher
Requires-Dist: pycryptodome
